<annotation>
	<folder>image_set</folder>
	<filename>IMG_20211110_132928.jpg</filename>
	<path>/home/christopher/git/puck-detection/image_set/IMG_20211110_132928.jpg</path>
	<source>
		<database>Unknown</database>
	</source>
	<size>
		<width>480</width>
		<height>640</height>
		<depth>3</depth>
	</size>
	<segmented>0</segmented>
	<object>
		<name>r</name>
		<pose>Unspecified</pose>
		<truncated>0</truncated>
		<difficult>0</difficult>
		<bndbox>
			<xmin>174</xmin>
			<ymin>499</ymin>
			<xmax>336</xmax>
			<ymax>608</ymax>
		</bndbox>
	</object>
	<object>
		<name>o</name>
		<pose>Unspecified</pose>
		<truncated>0</truncated>
		<difficult>0</difficult>
		<bndbox>
			<xmin>246</xmin>
			<ymin>406</ymin>
			<xmax>310</xmax>
			<ymax>433</ymax>
		</bndbox>
	</object>
	<object>
		<name>o</name>
		<pose>Unspecified</pose>
		<truncated>0</truncated>
		<difficult>0</difficult>
		<bndbox>
			<xmin>273</xmin>
			<ymin>377</ymin>
			<xmax>312</xmax>
			<ymax>393</ymax>
		</bndbox>
	</object>
	<object>
		<name>bl</name>
		<pose>Unspecified</pose>
		<truncated>0</truncated>
		<difficult>0</difficult>
		<bndbox>
			<xmin>342</xmin>
			<ymin>321</ymin>
			<xmax>477</xmax>
			<ymax>430</ymax>
		</bndbox>
	</object>
</annotation>
